gidgethub/__init__.py
gidgethub/abc.py
gidgethub/actions.py
gidgethub/aiohttp.py
gidgethub/apps.py
gidgethub/httpx.py
gidgethub/py.typed
gidgethub/routing.py
gidgethub/sansio.py
gidgethub/tornado.py
gidgethub-5.4.0.dist-info/licenses/LICENSE
gidgethub-5.4.0.dist-info/WHEEL
gidgethub-5.4.0.dist-info/METADATA
gidgethub-5.4.0.dist-info/RECORD
