Metadata-Version: 2.4
Name: gidgethub
Version: 5.4.0
Summary: An async GitHub API library
Keywords: github sans-io async
Author: Brett Cannon
Author-email: brett@python.org
Requires-Python: >=3.8
License: Apache
Classifier: Intended Audience :: Developers
Classifier: License :: OSI Approved :: Apache Software License
Classifier: Development Status :: 5 - Production/Stable
Classifier: Programming Language :: Python :: 3 :: Only
Classifier: Programming Language :: Python :: 3.8
Classifier: Programming Language :: Python :: 3.9
Classifier: Programming Language :: Python :: 3.10
Classifier: Programming Language :: Python :: 3.11
Classifier: Programming Language :: Python :: 3.12
Classifier: Programming Language :: Python :: 3.13
License-File: LICENSE
Requires-Dist: uritemplate>=3.0.1
Requires-Dist: PyJWT[crypto]>=2.4.0
Requires-Dist: aiohttp ; extra == "aiohttp"
Requires-Dist: aiohttp ; extra == "dev"
Requires-Dist: black ; extra == "dev"
Requires-Dist: coverage[toml]>=5.0.3 ; extra == "dev"
Requires-Dist: httpx ; extra == "dev"
Requires-Dist: mypy ; extra == "dev"
Requires-Dist: pytest-cov ; extra == "dev"
Requires-Dist: pytest-xdist ; extra == "dev"
Requires-Dist: tornado ; extra == "dev"
Requires-Dist: sphinx>=4.0.0 ; extra == "doc"
Requires-Dist: sphinx-rtd-theme>=0.5.2 ; extra == "doc"
Requires-Dist: httpx>=0.16.1 ; extra == "httpx"
Requires-Dist: importlib-resources ; extra == "test"
Requires-Dist: pytest>=5.4.1 ; extra == "test"
Requires-Dist: pytest-asyncio ; extra == "test"
Requires-Dist: pytest-tornasync ; extra == "test"
Requires-Dist: tornado ; extra == "tornado"
Project-URL: Documentation, https://gidgethub.readthedocs.io
Project-URL: Repository, https://github.com/brettcannon/gidgethub
Provides-Extra: aiohttp
Provides-Extra: dev
Provides-Extra: doc
Provides-Extra: httpx
Provides-Extra: test
Provides-Extra: tornado
